micom/__init__.py
micom/algorithms.py
micom/annotation.py
micom/community.py
micom/constants.py
micom/db.py
micom/deps.py
micom/duality.py
micom/elasticity.py
micom/logger.py
micom/measures.py
micom/media.py
micom/optcom.py
micom/problems.py
micom/qiime_formats.py
micom/solution.py
micom/stats.py
micom/taxonomy.py
micom/util.py
micom/data/__init__.py
micom/data/agora.csv
micom/data/e_coli_core.xml.gz
micom/data/artifacts/crc_tradeoff.csv
micom/data/artifacts/medium.qza
micom/data/artifacts/results.zip
micom/data/artifacts/species_models.qza
micom/data/templates/blobify.js
micom/data/templates/focal_interactions.html
micom/data/templates/growth.html
micom/data/templates/reduced.html
micom/data/templates/sample_heatmap.html
micom/data/templates/scores.html
micom/data/templates/tests.html
micom/data/templates/tradeoff.html
micom/interaction/__init__.py
micom/interaction/focal.py
micom/interaction/scores.py
micom/interaction/summary.py
micom/viz/__init__.py
micom/viz/association.py
micom/viz/core.py
micom/viz/exchanges.py
micom/viz/growth.py
micom/viz/interactions.py
micom/viz/tradeoff.py
micom/workflows/__init__.py
micom/workflows/build.py
micom/workflows/core.py
micom/workflows/db_media.py
micom/workflows/grow.py
micom/workflows/media.py
micom/workflows/results.py
micom/workflows/tradeoff.py
micom-0.37.1.dist-info/LICENSE
micom-0.37.1.dist-info/METADATA
micom-0.37.1.dist-info/WHEEL
micom-0.37.1.dist-info/top_level.txt
micom-0.37.1.dist-info/zip-safe
micom-0.37.1.dist-info/RECORD
