Metadata-Version: 2.4
Name: micom
Version: 0.37.1
Summary: Microbial community modeling based on cobrapy.
Home-page: https://github.com/micom-dev/micom
Author: Christian Diener
Author-email: mail@cdiener.com
License: Apache License 2.0
Keywords: microbiome,microbiota,modeling,metabolism,community,metabolic modeling
Classifier: Development Status :: 5 - Production/Stable
Classifier: Intended Audience :: Science/Research
Classifier: Topic :: Scientific/Engineering :: Bio-Informatics
Classifier: License :: OSI Approved :: Apache Software License
Classifier: Programming Language :: Python :: 3
Classifier: Programming Language :: Python :: 3.8
Classifier: Programming Language :: Python :: 3.9
Classifier: Programming Language :: Python :: 3.10
Classifier: Programming Language :: Python :: 3.11
Requires-Python: >=3.7
License-File: LICENSE
Requires-Dist: pandas>=2.0.0
Requires-Dist: cobra>=0.29.0
Requires-Dist: jinja2>=2.10.0
Requires-Dist: scikit-learn>=1.0
Requires-Dist: scipy>=1.8.1
Requires-Dist: symengine>=0.6.1
Requires-Dist: osqp<1.0.0,>=0.6.2
Requires-Dist: optlang>=1.8.2
Requires-Dist: highspy>=1.7.2
Dynamic: license-file
